regular_mesh_plotter/__init__.py
regular_mesh_plotter/_version.py
regular_mesh_plotter/core.py
regular_mesh_plotter-0.5.3.dist-info/LICENSE.txt
regular_mesh_plotter-0.5.3.dist-info/METADATA
regular_mesh_plotter-0.5.3.dist-info/WHEEL
regular_mesh_plotter-0.5.3.dist-info/top_level.txt
regular_mesh_plotter-0.5.3.dist-info/RECORD
