Metadata-Version: 2.1
Name: regular-mesh-plotter
Version: 0.5.3
Summary: A Python package for creating publication quality plots of regular mesh tallies with the underlying geometry
Author-email: Jonathan Shimwell <mail@jshimwell.com>
License: MIT License
Project-URL: Homepage, https://github.com/fusion-energy/regular_mesh_plotter
Project-URL: Bug Tracker, https://github.com/fusion-energy/regular_mesh_plotter/issues
Keywords: regular,mesh,openmc,tally,plot,slice
Classifier: Programming Language :: Python :: 3
Classifier: License :: OSI Approved :: MIT License
Classifier: Operating System :: OS Independent
Requires-Python: >=3.8
License-File: LICENSE.txt
Requires-Dist: numpy (>=1.21.1)
Requires-Dist: matplotlib (>=3.4.2)
Requires-Dist: trimesh
Requires-Dist: shapely
Requires-Dist: scipy
Requires-Dist: pandas
Requires-Dist: dagmc-geometry-slice-plotter
Requires-Dist: openmc-tally-unit-converter
Requires-Dist: setuptools-scm
Provides-Extra: tests
Requires-Dist: pytest ; extra == 'tests'
Requires-Dist: dagmc-h5m-file-inspector ; extra == 'tests'
Requires-Dist: pytest-cov (>=2.12.1) ; extra == 'tests'
Requires-Dist: openmc-dagmc-wrapper ; extra == 'tests'
Requires-Dist: openmc-plasma-source ; extra == 'tests'
Requires-Dist: regular-mesh-plotter ; extra == 'tests'
